{
"Times": [
{
"Time": "1 пара",
"Code": 1,
"TimeFrom": "0001-01-01T09:00:00",
"TimeTo": "0001-01-01T10:30:00"
},
{
"Time": "2 пара",
"Code": 2,
"TimeFrom": "0001-01-01T10:40:00",
"TimeTo": "0001-01-01T12:10:00"
},
{
"Time": "3 пара ",
"Code": 3,
"TimeFrom": "0001-01-01T12:20:00",
"TimeTo": "0001-01-01T13:50:00"
},
{
"Time": "4 пара",
"Code": 5,
"TimeFrom": "0001-01-01T14:30:00",
"TimeTo": "0001-01-01T16:00:00"
},
{
"Time": "5 пара",
"Code": 6,
"TimeFrom": "0001-01-01T16:10:00",
"TimeTo": "0001-01-01T17:40:00"
},
{
"Time": "6 пара",
"Code": 7,
"TimeFrom": "0001-01-01T18:20:00",
"TimeTo": "0001-01-01T19:50:00"
},
{
"Time": "7 пара",
"Code": 8,
"TimeFrom": "0001-01-01T20:00:00",
"TimeTo": "0001-01-01T21:30:00"
}
],
"Data": [
{
"Day": 1,
"DayNumber": 0,
"Time": {
"Time": "6 пара",
"Code": 7,
"TimeFrom": "0001-01-01T18:20:00",
"TimeTo": "0001-01-01T19:50:00"
},
"Class": {
"Code": "0051436",
"Name": "Актуальные вопросы философии техники [Пр]",
"TeacherFull": "Комаров Александр Иванович",
"Teacher": "Комаров А.И.",
"Form": "Очное"
},
"Group": {
"Code": "ПИН-21М",
"Name": "ПИН-21М"
},
"Room": {
"Code": 13,
"Name": "3128 (м)"
}
},
{
"Day": 1,
"DayNumber": 0,
"Time": {
"Time": "5 пара",
"Code": 6,
"TimeFrom": "0001-01-01T16:10:00",
"TimeTo": "0001-01-01T17:40:00"
},
"Class": {
"Code": "0051436",
"Name": "Актуальные вопросы философии техники [Пр]",
"TeacherFull": "Комаров Александр Иванович",
"Teacher": "Комаров А.И.",
"Form": "Очное"
},
"Group": {
"Code": "ПИН-21М",
"Name": "ПИН-21М"
},
"Room": {
"Code": 41,
"Name": "3109 (м)"
}
},
{
"Day": 1,
"DayNumber": 1,
"Time": {
"Time": "3 пара ",
"Code": 3,
"TimeFrom": "0001-01-01T12:20:00",
"TimeTo": "0001-01-01T13:50:00"
},
"Class": {
"Code": "0050742",
"Name": "Математическая лингвистика и обработка естественного языка [Лаб]",
"TeacherFull": "Городилов Алексей Владиславович",
"Teacher": "Городилов А.В.",
"Form": "Очное"
},
"Group": {
"Code": "ПИН-21М",
"Name": "ПИН-21М"
},
"Room": {
"Code": 45,
"Name": "3125 к (м)"
}
},
{
"Day": 1,
"DayNumber": 1,
"Time": {
"Time": "4 пара",
"Code": 5,
"TimeFrom": "0001-01-01T14:30:00",
"TimeTo": "0001-01-01T16:00:00"
},
"Class": {
"Code": "0050742",
"Name": "Математическая лингвистика и обработка естественного языка [Лаб]",
"TeacherFull": "Городилов Алексей Владиславович",
"Teacher": "Городилов А.В.",
"Form": "Очное"
},
"Group": {
"Code": "ПИН-21М",
"Name": "ПИН-21М"
},
"Room": {
"Code": 45,
"Name": "3125 к (м)"
}
},
{
"Day": 1,
"DayNumber": 1,
"Time": {
"Time": "6 пара",
"Code": 7,
"TimeFrom": "0001-01-01T18:20:00",
"TimeTo": "0001-01-01T19:50:00"
},
"Class": {
"Code": "0051082",
"Name": "Разработка мобильных приложений [Пр]",
"TeacherFull": "Городилов Алексей Владиславович",
"Teacher": "Городилов А.В.",
"Form": "Очное"
},
"Group": {
"Code": "ПИН-21М",
"Name": "ПИН-21М"
},
"Room": {
"Code": 14,
"Name": "3131 к (м)"
}
},
{
"Day": 1,
"DayNumber": 1,
"Time": {
"Time": "7 пара",
"Code": 8,
"TimeFrom": "0001-01-01T20:00:00",
"TimeTo": "0001-01-01T21:30:00"
},
"Class": {
"Code": "0051082",
"Name": "Разработка мобильных приложений [Пр]",
"TeacherFull": "Городилов Алексей Владиславович",
"Teacher": "Городилов А.В.",
"Form": "Очное"
},
"Group": {
"Code": "ПИН-21М",
"Name": "ПИН-21М"
},
"Room": {
"Code": 14,
"Name": "3131 к (м)"
}
},
{
"Day": 1,
"DayNumber": 1,
"Time": {
"Time": "5 пара",
"Code": 6,
"TimeFrom": "0001-01-01T16:10:00",
"TimeTo": "0001-01-01T17:40:00"
},
"Class": {
"Code": "0051752",
"Name": "Разработка мобильных приложений [Лек]",
"TeacherFull": "Городилов Алексей Владиславович",
"Teacher": "Городилов А.В.",
"Form": "Очное"
},
"Group": {
"Code": "ПИН-21М",
"Name": "ПИН-21М"
},
"Room": {
"Code": 8,
"Name": "3216 (м)"
}
},
{
"Day": 1,
"DayNumber": 2,
"Time": {
"Time": "6 пара",
"Code": 7,
"TimeFrom": "0001-01-01T18:20:00",
"TimeTo": "0001-01-01T19:50:00"
},
"Class": {
"Code": "0051436",
"Name": "Актуальные вопросы философии техники [Пр]",
"TeacherFull": "Комаров Александр Иванович",
"Teacher": "Комаров А.И.",
"Form": "Очное"
},
"Group": {
"Code": "ПИН-21М",
"Name": "ПИН-21М"
},
"Room": {
"Code": 13,
"Name": "3128 (м)"
}
},
{
"Day": 1,
"DayNumber": 2,
"Time": {
"Time": "5 пара",
"Code": 6,
"TimeFrom": "0001-01-01T16:10:00",
"TimeTo": "0001-01-01T17:40:00"
},
"Class": {
"Code": "0051436",
"Name": "Актуальные вопросы философии техники [Пр]",
"TeacherFull": "Комаров Александр Иванович",
"Teacher": "Комаров А.И.",
"Form": "Очное"
},
"Group": {
"Code": "ПИН-21М",
"Name": "ПИН-21М"
},
"Room": {
"Code": 41,
"Name": "3109 (м)"
}
},
{
"Day": 1,
"DayNumber": 3,
"Time": {
"Time": "3 пара ",
"Code": 3,
"TimeFrom": "0001-01-01T12:20:00",
"TimeTo": "0001-01-01T13:50:00"
},
"Class": {
"Code": "0050742",
"Name": "Математическая лингвистика и обработка естественного языка [Лаб]",
"TeacherFull": "Городилов Алексей Владиславович",
"Teacher": "Городилов А.В.",
"Form": "Очное"
},
"Group": {
"Code": "ПИН-21М",
"Name": "ПИН-21М"
},
"Room": {
"Code": 45,
"Name": "3125 к (м)"
}
},
{
"Day": 1,
"DayNumber": 3,
"Time": {
"Time": "4 пара",
"Code": 5,
"TimeFrom": "0001-01-01T14:30:00",
"TimeTo": "0001-01-01T16:00:00"
},
"Class": {
"Code": "0050742",
"Name": "Математическая лингвистика и обработка естественного языка [Лаб]",
"TeacherFull": "Городилов Алексей Владиславович",
"Teacher": "Городилов А.В.",
"Form": "Очное"
},
"Group": {
"Code": "ПИН-21М",
"Name": "ПИН-21М"
},
"Room": {
"Code": 45,
"Name": "3125 к (м)"
}
},
{
"Day": 1,
"DayNumber": 3,
"Time": {
"Time": "6 пара",
"Code": 7,
"TimeFrom": "0001-01-01T18:20:00",
"TimeTo": "0001-01-01T19:50:00"
},
"Class": {
"Code": "0051082",
"Name": "Разработка мобильных приложений [Пр]",
"TeacherFull": "Городилов Алексей Владиславович",
"Teacher": "Городилов А.В.",
"Form": "Очное"
},
"Group": {
"Code": "ПИН-21М",
"Name": "ПИН-21М"
},
"Room": {
"Code": 14,
"Name": "3131 к (м)"
}
},
{
"Day": 1,
"DayNumber": 3,
"Time": {
"Time": "7 пара",
"Code": 8,
"TimeFrom": "0001-01-01T20:00:00",
"TimeTo": "0001-01-01T21:30:00"
},
"Class": {
"Code": "0051082",
"Name": "Разработка мобильных приложений [Пр]",
"TeacherFull": "Городилов Алексей Владиславович",
"Teacher": "Городилов А.В.",
"Form": "Очное"
},
"Group": {
"Code": "ПИН-21М",
"Name": "ПИН-21М"
},
"Room": {
"Code": 14,
"Name": "3131 к (м)"
}
},
{
"Day": 1,
"DayNumber": 3,
"Time": {
"Time": "5 пара",
"Code": 6,
"TimeFrom": "0001-01-01T16:10:00",
"TimeTo": "0001-01-01T17:40:00"
},
"Class": {
"Code": "0051752",
"Name": "Разработка мобильных приложений [Лек]",
"TeacherFull": "Городилов Алексей Владиславович",
"Teacher": "Городилов А.В.",
"Form": "Очное"
},
"Group": {
"Code": "ПИН-21М",
"Name": "ПИН-21М"
},
"Room": {
"Code": 8,
"Name": "3216 (м)"
}
},
{
"Day": 2,
"DayNumber": 0,
"Time": {
"Time": "7 пара",
"Code": 8,
"TimeFrom": "0001-01-01T20:00:00",
"TimeTo": "0001-01-01T21:30:00"
},
"Class": {
"Code": "0051436",
"Name": "Актуальные вопросы философии техники [Пр]",
"TeacherFull": "Комаров Александр Иванович",
"Teacher": "Комаров А.И.",
"Form": "Очное"
},
"Group": {
"Code": "ПИН-21М",
"Name": "ПИН-21М"
},
"Room": {
"Code": 44,
"Name": "3116 (м)"
}
},
{
"Day": 2,
"DayNumber": 0,
"Time": {
"Time": "6 пара",
"Code": 7,
"TimeFrom": "0001-01-01T18:20:00",
"TimeTo": "0001-01-01T19:50:00"
},
"Class": {
"Code": "0052439",
"Name": "Методология научных исследований [Пр]",
"TeacherFull": "Гагарина Лариса Геннадьевна",
"Teacher": "Гагарина Л.Г.",
"Form": "Очное"
},
"Group": {
"Code": "ПИН-21М",
"Name": "ПИН-21М"
},
"Room": {
"Code": 43,
"Name": "3129 (м)"
}
},
{
"Day": 2,
"DayNumber": 0,
"Time": {
"Time": "2 пара",
"Code": 2,
"TimeFrom": "0001-01-01T10:40:00",
"TimeTo": "0001-01-01T12:10:00"
},
"Class": {
"Code": "0053041",
"Name": "Практическая подготовка",
"TeacherFull": "Преподаватель У.П.",
"Teacher": "Преподаватель У..",
"Form": "Очное"
},
"Group": {
"Code": "ПИН-21М",
"Name": "ПИН-21М"
},
"Room": {
"Code": 233,
"Name": "Аудитория практической подготовки СПИНТЕХ 6"
}
},
{
"Day": 2,
"DayNumber": 0,
"Time": {
"Time": "1 пара",
"Code": 1,
"TimeFrom": "0001-01-01T09:00:00",
"TimeTo": "0001-01-01T10:30:00"
},
"Class": {
"Code": "0053041",
"Name": "Практическая подготовка",
"TeacherFull": "Преподаватель У.П.",
"Teacher": "Преподаватель У..",
"Form": "Очное"
},
"Group": {
"Code": "ПИН-21М",
"Name": "ПИН-21М"
},
"Room": {
"Code": 233,
"Name": "Аудитория практической подготовки СПИНТЕХ 6"
}
},
{
"Day": 2,
"DayNumber": 0,
"Time": {
"Time": "3 пара ",
"Code": 3,
"TimeFrom": "0001-01-01T12:20:00",
"TimeTo": "0001-01-01T13:50:00"
},
"Class": {
"Code": "0053041",
"Name": "Практическая подготовка",
"TeacherFull": "Преподаватель У.П.",
"Teacher": "Преподаватель У..",
"Form": "Очное"
},
"Group": {
"Code": "ПИН-21М",
"Name": "ПИН-21М"
},
"Room": {
"Code": 233,
"Name": "Аудитория практической подготовки СПИНТЕХ 6"
}
},
{
"Day": 2,
"DayNumber": 0,
"Time": {
"Time": "4 пара",
"Code": 5,
"TimeFrom": "0001-01-01T14:30:00",
"TimeTo": "0001-01-01T16:00:00"
},
"Class": {
"Code": "0053041",
"Name": "Практическая подготовка",
"TeacherFull": "Преподаватель У.П.",
"Teacher": "Преподаватель У..",
"Form": "Очное"
},
"Group": {
"Code": "ПИН-21М",
"Name": "ПИН-21М"
},
"Room": {
"Code": 233,
"Name": "Аудитория практической подготовки СПИНТЕХ 6"
}
},
{
"Day": 2,
"DayNumber": 0,
"Time": {
"Time": "5 пара",
"Code": 6,
"TimeFrom": "0001-01-01T16:10:00",
"TimeTo": "0001-01-01T17:40:00"
},
"Class": {
"Code": "0053041",
"Name": "Практическая подготовка",
"TeacherFull": "Преподаватель У.П.",
"Teacher": "Преподаватель У..",
"Form": "Очное"
},
"Group": {
"Code": "ПИН-21М",
"Name": "ПИН-21М"
},
"Room": {
"Code": 233,
"Name": "Аудитория практической подготовки СПИНТЕХ 6"
}
},
{
"Day": 2,
"DayNumber": 1,
"Time": {
"Time": "6 пара",
"Code": 7,
"TimeFrom": "0001-01-01T18:20:00",
"TimeTo": "0001-01-01T19:50:00"
},
"Class": {
"Code": "0052439",
"Name": "Методология научных исследований [Пр]",
"TeacherFull": "Гагарина Лариса Геннадьевна",
"Teacher": "Гагарина Л.Г.",
"Form": "Очное"
},
"Group": {
"Code": "ПИН-21М",
"Name": "ПИН-21М"
},
"Room": {
"Code": 43,
"Name": "3129 (м)"
}
},
{
"Day": 2,
"DayNumber": 1,
"Time": {
"Time": "5 пара",
"Code": 6,
"TimeFrom": "0001-01-01T16:10:00",
"TimeTo": "0001-01-01T17:40:00"
},
"Class": {
"Code": "0053041",
"Name": "Практическая подготовка",
"TeacherFull": "Преподаватель У.П.",
"Teacher": "Преподаватель У..",
"Form": "Очное"
},
"Group": {
"Code": "ПИН-21М",
"Name": "ПИН-21М"
},
"Room": {
"Code": 233,
"Name": "Аудитория практической подготовки СПИНТЕХ 6"
}
},
{
"Day": 2,
"DayNumber": 1,
"Time": {
"Time": "4 пара",
"Code": 5,
"TimeFrom": "0001-01-01T14:30:00",
"TimeTo": "0001-01-01T16:00:00"
},
"Class": {
"Code": "0053041",
"Name": "Практическая подготовка",
"TeacherFull": "Преподаватель У.П.",
"Teacher": "Преподаватель У..",
"Form": "Очное"
},
"Group": {
"Code": "ПИН-21М",
"Name": "ПИН-21М"
},
"Room": {
"Code": 233,
"Name": "Аудитория практической подготовки СПИНТЕХ 6"
}
},
{
"Day": 2,
"DayNumber": 1,
"Time": {
"Time": "3 пара ",
"Code": 3,
"TimeFrom": "0001-01-01T12:20:00",
"TimeTo": "0001-01-01T13:50:00"
},
"Class": {
"Code": "0053041",
"Name": "Практическая подготовка",
"TeacherFull": "Преподаватель У.П.",
"Teacher": "Преподаватель У..",
"Form": "Очное"
},
"Group": {
"Code": "ПИН-21М",
"Name": "ПИН-21М"
},
"Room": {
"Code": 233,
"Name": "Аудитория практической подготовки СПИНТЕХ 6"
}
},
{
"Day": 2,
"DayNumber": 1,
"Time": {
"Time": "2 пара",
"Code": 2,
"TimeFrom": "0001-01-01T10:40:00",
"TimeTo": "0001-01-01T12:10:00"
},
"Class": {
"Code": "0053041",
"Name": "Практическая подготовка",
"TeacherFull": "Преподаватель У.П.",
"Teacher": "Преподаватель У..",
"Form": "Очное"
},
"Group": {
"Code": "ПИН-21М",
"Name": "ПИН-21М"
},
"Room": {
"Code": 233,
"Name": "Аудитория практической подготовки СПИНТЕХ 6"
}
},
{
"Day": 2,
"DayNumber": 1,
"Time": {
"Time": "1 пара",
"Code": 1,
"TimeFrom": "0001-01-01T09:00:00",
"TimeTo": "0001-01-01T10:30:00"
},
"Class": {
"Code": "0053041",
"Name": "Практическая подготовка",
"TeacherFull": "Преподаватель У.П.",
"Teacher": "Преподаватель У..",
"Form": "Очное"
},
"Group": {
"Code": "ПИН-21М",
"Name": "ПИН-21М"
},
"Room": {
"Code": 233,
"Name": "Аудитория практической подготовки СПИНТЕХ 6"
}
},
{
"Day": 2,
"DayNumber": 2,
"Time": {
"Time": "7 пара",
"Code": 8,
"TimeFrom": "0001-01-01T20:00:00",
"TimeTo": "0001-01-01T21:30:00"
},
"Class": {
"Code": "0051436",
"Name": "Актуальные вопросы философии техники [Пр]",
"TeacherFull": "Комаров Александр Иванович",
"Teacher": "Комаров А.И.",
"Form": "Очное"
},
"Group": {
"Code": "ПИН-21М",
"Name": "ПИН-21М"
},
"Room": {
"Code": 44,
"Name": "3116 (м)"
}
},
{
"Day": 2,
"DayNumber": 2,
"Time": {
"Time": "6 пара",
"Code": 7,
"TimeFrom": "0001-01-01T18:20:00",
"TimeTo": "0001-01-01T19:50:00"
},
"Class": {
"Code": "0052439",
"Name": "Методология научных исследований [Пр]",
"TeacherFull": "Гагарина Лариса Геннадьевна",
"Teacher": "Гагарина Л.Г.",
"Form": "Очное"
},
"Group": {
"Code": "ПИН-21М",
"Name": "ПИН-21М"
},
"Room": {
"Code": 43,
"Name": "3129 (м)"
}
},
{
"Day": 2,
"DayNumber": 2,
"Time": {
"Time": "1 пара",
"Code": 1,
"TimeFrom": "0001-01-01T09:00:00",
"TimeTo": "0001-01-01T10:30:00"
},
"Class": {
"Code": "0053041",
"Name": "Практическая подготовка",
"TeacherFull": "Преподаватель У.П.",
"Teacher": "Преподаватель У..",
"Form": "Очное"
},
"Group": {
"Code": "ПИН-21М",
"Name": "ПИН-21М"
},
"Room": {
"Code": 233,
"Name": "Аудитория практической подготовки СПИНТЕХ 6"
}
},
{
"Day": 2,
"DayNumber": 2,
"Time": {
"Time": "2 пара",
"Code": 2,
"TimeFrom": "0001-01-01T10:40:00",
"TimeTo": "0001-01-01T12:10:00"
},
"Class": {
"Code": "0053041",
"Name": "Практическая подготовка",
"TeacherFull": "Преподаватель У.П.",
"Teacher": "Преподаватель У..",
"Form": "Очное"
},
"Group": {
"Code": "ПИН-21М",
"Name": "ПИН-21М"
},
"Room": {
"Code": 233,
"Name": "Аудитория практической подготовки СПИНТЕХ 6"
}
},
{
"Day": 2,
"DayNumber": 2,
"Time": {
"Time": "5 пара",
"Code": 6,
"TimeFrom": "0001-01-01T16:10:00",
"TimeTo": "0001-01-01T17:40:00"
},
"Class": {
"Code": "0053041",
"Name": "Практическая подготовка",
"TeacherFull": "Преподаватель У.П.",
"Teacher": "Преподаватель У..",
"Form": "Очное"
},
"Group": {
"Code": "ПИН-21М",
"Name": "ПИН-21М"
},
"Room": {
"Code": 233,
"Name": "Аудитория практической подготовки СПИНТЕХ 6"
}
},
{
"Day": 2,
"DayNumber": 2,
"Time": {
"Time": "3 пара ",
"Code": 3,
"TimeFrom": "0001-01-01T12:20:00",
"TimeTo": "0001-01-01T13:50:00"
},
"Class": {
"Code": "0053041",
"Name": "Практическая подготовка",
"TeacherFull": "Преподаватель У.П.",
"Teacher": "Преподаватель У..",
"Form": "Очное"
},
"Group": {
"Code": "ПИН-21М",
"Name": "ПИН-21М"
},
"Room": {
"Code": 233,
"Name": "Аудитория практической подготовки СПИНТЕХ 6"
}
},
{
"Day": 2,
"DayNumber": 2,
"Time": {
"Time": "4 пара",
"Code": 5,
"TimeFrom": "0001-01-01T14:30:00",
"TimeTo": "0001-01-01T16:00:00"
},
"Class": {
"Code": "0053041",
"Name": "Практическая подготовка",
"TeacherFull": "Преподаватель У.П.",
"Teacher": "Преподаватель У..",
"Form": "Очное"
},
"Group": {
"Code": "ПИН-21М",
"Name": "ПИН-21М"
},
"Room": {
"Code": 233,
"Name": "Аудитория практической подготовки СПИНТЕХ 6"
}
},
{
"Day": 2,
"DayNumber": 3,
"Time": {
"Time": "6 пара",
"Code": 7,
"TimeFrom": "0001-01-01T18:20:00",
"TimeTo": "0001-01-01T19:50:00"
},
"Class": {
"Code": "0052439",
"Name": "Методология научных исследований [Пр]",
"TeacherFull": "Гагарина Лариса Геннадьевна",
"Teacher": "Гагарина Л.Г.",
"Form": "Очное"
},
"Group": {
"Code": "ПИН-21М",
"Name": "ПИН-21М"
},
"Room": {
"Code": 43,
"Name": "3129 (м)"
}
},
{
"Day": 2,
"DayNumber": 3,
"Time": {
"Time": "4 пара",
"Code": 5,
"TimeFrom": "0001-01-01T14:30:00",
"TimeTo": "0001-01-01T16:00:00"
},
"Class": {
"Code": "0053041",
"Name": "Практическая подготовка",
"TeacherFull": "Преподаватель У.П.",
"Teacher": "Преподаватель У..",
"Form": "Очное"
},
"Group": {
"Code": "ПИН-21М",
"Name": "ПИН-21М"
},
"Room": {
"Code": 233,
"Name": "Аудитория практической подготовки СПИНТЕХ 6"
}
},
{
"Day": 2,
"DayNumber": 3,
"Time": {
"Time": "5 пара",
"Code": 6,
"TimeFrom": "0001-01-01T16:10:00",
"TimeTo": "0001-01-01T17:40:00"
},
"Class": {
"Code": "0053041",
"Name": "Практическая подготовка",
"TeacherFull": "Преподаватель У.П.",
"Teacher": "Преподаватель У..",
"Form": "Очное"
},
"Group": {
"Code": "ПИН-21М",
"Name": "ПИН-21М"
},
"Room": {
"Code": 233,
"Name": "Аудитория практической подготовки СПИНТЕХ 6"
}
},
{
"Day": 2,
"DayNumber": 3,
"Time": {
"Time": "2 пара",
"Code": 2,
"TimeFrom": "0001-01-01T10:40:00",
"TimeTo": "0001-01-01T12:10:00"
},
"Class": {
"Code": "0053041",
"Name": "Практическая подготовка",
"TeacherFull": "Преподаватель У.П.",
"Teacher": "Преподаватель У..",
"Form": "Очное"
},
"Group": {
"Code": "ПИН-21М",
"Name": "ПИН-21М"
},
"Room": {
"Code": 233,
"Name": "Аудитория практической подготовки СПИНТЕХ 6"
}
},
{
"Day": 2,
"DayNumber": 3,
"Time": {
"Time": "3 пара ",
"Code": 3,
"TimeFrom": "0001-01-01T12:20:00",
"TimeTo": "0001-01-01T13:50:00"
},
"Class": {
"Code": "0053041",
"Name": "Практическая подготовка",
"TeacherFull": "Преподаватель У.П.",
"Teacher": "Преподаватель У..",
"Form": "Очное"
},
"Group": {
"Code": "ПИН-21М",
"Name": "ПИН-21М"
},
"Room": {
"Code": 233,
"Name": "Аудитория практической подготовки СПИНТЕХ 6"
}
},
{
"Day": 2,
"DayNumber": 3,
"Time": {
"Time": "1 пара",
"Code": 1,
"TimeFrom": "0001-01-01T09:00:00",
"TimeTo": "0001-01-01T10:30:00"
},
"Class": {
"Code": "0053041",
"Name": "Практическая подготовка",
"TeacherFull": "Преподаватель У.П.",
"Teacher": "Преподаватель У..",
"Form": "Очное"
},
"Group": {
"Code": "ПИН-21М",
"Name": "ПИН-21М"
},
"Room": {
"Code": 233,
"Name": "Аудитория практической подготовки СПИНТЕХ 6"
}
},
{
"Day": 3,
"DayNumber": 0,
"Time": {
"Time": "2 пара",
"Code": 2,
"TimeFrom": "0001-01-01T10:40:00",
"TimeTo": "0001-01-01T12:10:00"
},
"Class": {
"Code": "0047801",
"Name": "Военная подготовка",
"TeacherFull": "Преподаватель УВЦ",
"Teacher": "Преподаватель УВЦ",
"Form": "Очное"
},
"Group": {
"Code": "ПИН-21М",
"Name": "ПИН-21М"
},
"Room": {
"Code": 161,
"Name": "УВЦ2"
}
},
{
"Day": 3,
"DayNumber": 0,
"Time": {
"Time": "3 пара ",
"Code": 3,
"TimeFrom": "0001-01-01T12:20:00",
"TimeTo": "0001-01-01T13:50:00"
},
"Class": {
"Code": "0047801",
"Name": "Военная подготовка",
"TeacherFull": "Преподаватель УВЦ",
"Teacher": "Преподаватель УВЦ",
"Form": "Очное"
},
"Group": {
"Code": "ПИН-21М",
"Name": "ПИН-21М"
},
"Room": {
"Code": 161,
"Name": "УВЦ2"
}
},
{
"Day": 3,
"DayNumber": 0,
"Time": {
"Time": "6 пара",
"Code": 7,
"TimeFrom": "0001-01-01T18:20:00",
"TimeTo": "0001-01-01T19:50:00"
},
"Class": {
"Code": "0047801",
"Name": "Военная подготовка",
"TeacherFull": "Преподаватель УВЦ",
"Teacher": "Преподаватель УВЦ",
"Form": "Очное"
},
"Group": {
"Code": "ПИН-21М",
"Name": "ПИН-21М"
},
"Room": {
"Code": 161,
"Name": "УВЦ2"
}
},
{
"Day": 3,
"DayNumber": 0,
"Time": {
"Time": "7 пара",
"Code": 8,
"TimeFrom": "0001-01-01T20:00:00",
"TimeTo": "0001-01-01T21:30:00"
},
"Class": {
"Code": "0047801",
"Name": "Военная подготовка",
"TeacherFull": "Преподаватель УВЦ",
"Teacher": "Преподаватель УВЦ",
"Form": "Очное"
},
"Group": {
"Code": "ПИН-21М",
"Name": "ПИН-21М"
},
"Room": {
"Code": 161,
"Name": "УВЦ2"
}
},
{
"Day": 3,
"DayNumber": 0,
"Time": {
"Time": "4 пара",
"Code": 5,
"TimeFrom": "0001-01-01T14:30:00",
"TimeTo": "0001-01-01T16:00:00"
},
"Class": {
"Code": "0047801",
"Name": "Военная подготовка",
"TeacherFull": "Преподаватель УВЦ",
"Teacher": "Преподаватель УВЦ",
"Form": "Очное"
},
"Group": {
"Code": "ПИН-21М",
"Name": "ПИН-21М"
},
"Room": {
"Code": 161,
"Name": "УВЦ2"
}
},
{
"Day": 3,
"DayNumber": 0,
"Time": {
"Time": "5 пара",
"Code": 6,
"TimeFrom": "0001-01-01T16:10:00",
"TimeTo": "0001-01-01T17:40:00"
},
"Class": {
"Code": "0047801",
"Name": "Военная подготовка",
"TeacherFull": "Преподаватель УВЦ",
"Teacher": "Преподаватель УВЦ",
"Form": "Очное"
},
"Group": {
"Code": "ПИН-21М",
"Name": "ПИН-21М"
},
"Room": {
"Code": 161,
"Name": "УВЦ2"
}
},
{
"Day": 3,
"DayNumber": 0,
"Time": {
"Time": "1 пара",
"Code": 1,
"TimeFrom": "0001-01-01T09:00:00",
"TimeTo": "0001-01-01T10:30:00"
},
"Class": {
"Code": "0047801",
"Name": "Военная подготовка",
"TeacherFull": "Преподаватель УВЦ",
"Teacher": "Преподаватель УВЦ",
"Form": "Очное"
},
"Group": {
"Code": "ПИН-21М",
"Name": "ПИН-21М"
},
"Room": {
"Code": 161,
"Name": "УВЦ2"
}
},
{
"Day": 3,
"DayNumber": 1,
"Time": {
"Time": "1 пара",
"Code": 1,
"TimeFrom": "0001-01-01T09:00:00",
"TimeTo": "0001-01-01T10:30:00"
},
"Class": {
"Code": "0047801",
"Name": "Военная подготовка",
"TeacherFull": "Преподаватель УВЦ",
"Teacher": "Преподаватель УВЦ",
"Form": "Очное"
},
"Group": {
"Code": "ПИН-21М",
"Name": "ПИН-21М"
},
"Room": {
"Code": 161,
"Name": "УВЦ2"
}
},
{
"Day": 3,
"DayNumber": 1,
"Time": {
"Time": "2 пара",
"Code": 2,
"TimeFrom": "0001-01-01T10:40:00",
"TimeTo": "0001-01-01T12:10:00"
},
"Class": {
"Code": "0047801",
"Name": "Военная подготовка",
"TeacherFull": "Преподаватель УВЦ",
"Teacher": "Преподаватель УВЦ",
"Form": "Очное"
},
"Group": {
"Code": "ПИН-21М",
"Name": "ПИН-21М"
},
"Room": {
"Code": 161,
"Name": "УВЦ2"
}
},
{
"Day": 3,
"DayNumber": 1,
"Time": {
"Time": "4 пара",
"Code": 5,
"TimeFrom": "0001-01-01T14:30:00",
"TimeTo": "0001-01-01T16:00:00"
},
"Class": {
"Code": "0047801",
"Name": "Военная подготовка",
"TeacherFull": "Преподаватель УВЦ",
"Teacher": "Преподаватель УВЦ",
"Form": "Очное"
},
"Group": {
"Code": "ПИН-21М",
"Name": "ПИН-21М"
},
"Room": {
"Code": 161,
"Name": "УВЦ2"
}
},
{
"Day": 3,
"DayNumber": 1,
"Time": {
"Time": "5 пара",
"Code": 6,
"TimeFrom": "0001-01-01T16:10:00",
"TimeTo": "0001-01-01T17:40:00"
},
"Class": {
"Code": "0047801",
"Name": "Военная подготовка",
"TeacherFull": "Преподаватель УВЦ",
"Teacher": "Преподаватель УВЦ",
"Form": "Очное"
},
"Group": {
"Code": "ПИН-21М",
"Name": "ПИН-21М"
},
"Room": {
"Code": 161,
"Name": "УВЦ2"
}
},
{
"Day": 3,
"DayNumber": 1,
"Time": {
"Time": "6 пара",
"Code": 7,
"TimeFrom": "0001-01-01T18:20:00",
"TimeTo": "0001-01-01T19:50:00"
},
"Class": {
"Code": "0047801",
"Name": "Военная подготовка",
"TeacherFull": "Преподаватель УВЦ",
"Teacher": "Преподаватель УВЦ",
"Form": "Очное"
},
"Group": {
"Code": "ПИН-21М",
"Name": "ПИН-21М"
},
"Room": {
"Code": 161,
"Name": "УВЦ2"
}
},
{
"Day": 3,
"DayNumber": 1,
"Time": {
"Time": "3 пара ",
"Code": 3,
"TimeFrom": "0001-01-01T12:20:00",
"TimeTo": "0001-01-01T13:50:00"
},
"Class": {
"Code": "0047801",
"Name": "Военная подготовка",
"TeacherFull": "Преподаватель УВЦ",
"Teacher": "Преподаватель УВЦ",
"Form": "Очное"
},
"Group": {
"Code": "ПИН-21М",
"Name": "ПИН-21М"
},
"Room": {
"Code": 161,
"Name": "УВЦ2"
}
},
{
"Day": 3,
"DayNumber": 1,
"Time": {
"Time": "7 пара",
"Code": 8,
"TimeFrom": "0001-01-01T20:00:00",
"TimeTo": "0001-01-01T21:30:00"
},
"Class": {
"Code": "0047801",
"Name": "Военная подготовка",
"TeacherFull": "Преподаватель УВЦ",
"Teacher": "Преподаватель УВЦ",
"Form": "Очное"
},
"Group": {
"Code": "ПИН-21М",
"Name": "ПИН-21М"
},
"Room": {
"Code": 161,
"Name": "УВЦ2"
}
},
{
"Day": 3,
"DayNumber": 2,
"Time": {
"Time": "7 пара",
"Code": 8,
"TimeFrom": "0001-01-01T20:00:00",
"TimeTo": "0001-01-01T21:30:00"
},
"Class": {
"Code": "0047801",
"Name": "Военная подготовка",
"TeacherFull": "Преподаватель УВЦ",
"Teacher": "Преподаватель УВЦ",
"Form": "Очное"
},
"Group": {
"Code": "ПИН-21М",
"Name": "ПИН-21М"
},
"Room": {
"Code": 161,
"Name": "УВЦ2"
}
},
{
"Day": 3,
"DayNumber": 2,
"Time": {
"Time": "3 пара ",
"Code": 3,
"TimeFrom": "0001-01-01T12:20:00",
"TimeTo": "0001-01-01T13:50:00"
},
"Class": {
"Code": "0047801",
"Name": "Военная подготовка",
"TeacherFull": "Преподаватель УВЦ",
"Teacher": "Преподаватель УВЦ",
"Form": "Очное"
},
"Group": {
"Code": "ПИН-21М",
"Name": "ПИН-21М"
},
"Room": {
"Code": 161,
"Name": "УВЦ2"
}
},
{
"Day": 3,
"DayNumber": 2,
"Time": {
"Time": "6 пара",
"Code": 7,
"TimeFrom": "0001-01-01T18:20:00",
"TimeTo": "0001-01-01T19:50:00"
},
"Class": {
"Code": "0047801",
"Name": "Военная подготовка",
"TeacherFull": "Преподаватель УВЦ",
"Teacher": "Преподаватель УВЦ",
"Form": "Очное"
},
"Group": {
"Code": "ПИН-21М",
"Name": "ПИН-21М"
},
"Room": {
"Code": 161,
"Name": "УВЦ2"
}
},
{
"Day": 3,
"DayNumber": 2,
"Time": {
"Time": "5 пара",
"Code": 6,
"TimeFrom": "0001-01-01T16:10:00",
"TimeTo": "0001-01-01T17:40:00"
},
"Class": {
"Code": "0047801",
"Name": "Военная подготовка",
"TeacherFull": "Преподаватель УВЦ",
"Teacher": "Преподаватель УВЦ",
"Form": "Очное"
},
"Group": {
"Code": "ПИН-21М",
"Name": "ПИН-21М"
},
"Room": {
"Code": 161,
"Name": "УВЦ2"
}
},
{
"Day": 3,
"DayNumber": 2,
"Time": {
"Time": "4 пара",
"Code": 5,
"TimeFrom": "0001-01-01T14:30:00",
"TimeTo": "0001-01-01T16:00:00"
},
"Class": {
"Code": "0047801",
"Name": "Военная подготовка",
"TeacherFull": "Преподаватель УВЦ",
"Teacher": "Преподаватель УВЦ",
"Form": "Очное"
},
"Group": {
"Code": "ПИН-21М",
"Name": "ПИН-21М"
},
"Room": {
"Code": 161,
"Name": "УВЦ2"
}
},
{
"Day": 3,
"DayNumber": 2,
"Time": {
"Time": "2 пара",
"Code": 2,
"TimeFrom": "0001-01-01T10:40:00",
"TimeTo": "0001-01-01T12:10:00"
},
"Class": {
"Code": "0047801",
"Name": "Военная подготовка",
"TeacherFull": "Преподаватель УВЦ",
"Teacher": "Преподаватель УВЦ",
"Form": "Очное"
},
"Group": {
"Code": "ПИН-21М",
"Name": "ПИН-21М"
},
"Room": {
"Code": 161,
"Name": "УВЦ2"
}
},
{
"Day": 3,
"DayNumber": 2,
"Time": {
"Time": "1 пара",
"Code": 1,
"TimeFrom": "0001-01-01T09:00:00",
"TimeTo": "0001-01-01T10:30:00"
},
"Class": {
"Code": "0047801",
"Name": "Военная подготовка",
"TeacherFull": "Преподаватель УВЦ",
"Teacher": "Преподаватель УВЦ",
"Form": "Очное"
},
"Group": {
"Code": "ПИН-21М",
"Name": "ПИН-21М"
},
"Room": {
"Code": 161,
"Name": "УВЦ2"
}
},
{
"Day": 3,
"DayNumber": 3,
"Time": {
"Time": "5 пара",
"Code": 6,
"TimeFrom": "0001-01-01T16:10:00",
"TimeTo": "0001-01-01T17:40:00"
},
"Class": {
"Code": "0047801",
"Name": "Военная подготовка",
"TeacherFull": "Преподаватель УВЦ",
"Teacher": "Преподаватель УВЦ",
"Form": "Очное"
},
"Group": {
"Code": "ПИН-21М",
"Name": "ПИН-21М"
},
"Room": {
"Code": 161,
"Name": "УВЦ2"
}
},
{
"Day": 3,
"DayNumber": 3,
"Time": {
"Time": "1 пара",
"Code": 1,
"TimeFrom": "0001-01-01T09:00:00",
"TimeTo": "0001-01-01T10:30:00"
},
"Class": {
"Code": "0047801",
"Name": "Военная подготовка",
"TeacherFull": "Преподаватель УВЦ",
"Teacher": "Преподаватель УВЦ",
"Form": "Очное"
},
"Group": {
"Code": "ПИН-21М",
"Name": "ПИН-21М"
},
"Room": {
"Code": 161,
"Name": "УВЦ2"
}
},
{
"Day": 3,
"DayNumber": 3,
"Time": {
"Time": "2 пара",
"Code": 2,
"TimeFrom": "0001-01-01T10:40:00",
"TimeTo": "0001-01-01T12:10:00"
},
"Class": {
"Code": "0047801",
"Name": "Военная подготовка",
"TeacherFull": "Преподаватель УВЦ",
"Teacher": "Преподаватель УВЦ",
"Form": "Очное"
},
"Group": {
"Code": "ПИН-21М",
"Name": "ПИН-21М"
},
"Room": {
"Code": 161,
"Name": "УВЦ2"
}
},
{
"Day": 3,
"DayNumber": 3,
"Time": {
"Time": "4 пара",
"Code": 5,
"TimeFrom": "0001-01-01T14:30:00",
"TimeTo": "0001-01-01T16:00:00"
},
"Class": {
"Code": "0047801",
"Name": "Военная подготовка",
"TeacherFull": "Преподаватель УВЦ",
"Teacher": "Преподаватель УВЦ",
"Form": "Очное"
},
"Group": {
"Code": "ПИН-21М",
"Name": "ПИН-21М"
},
"Room": {
"Code": 161,
"Name": "УВЦ2"
}
},
{
"Day": 3,
"DayNumber": 3,
"Time": {
"Time": "6 пара",
"Code": 7,
"TimeFrom": "0001-01-01T18:20:00",
"TimeTo": "0001-01-01T19:50:00"
},
"Class": {
"Code": "0047801",
"Name": "Военная подготовка",
"TeacherFull": "Преподаватель УВЦ",
"Teacher": "Преподаватель УВЦ",
"Form": "Очное"
},
"Group": {
"Code": "ПИН-21М",
"Name": "ПИН-21М"
},
"Room": {
"Code": 161,
"Name": "УВЦ2"
}
},
{
"Day": 3,
"DayNumber": 3,
"Time": {
"Time": "3 пара ",
"Code": 3,
"TimeFrom": "0001-01-01T12:20:00",
"TimeTo": "0001-01-01T13:50:00"
},
"Class": {
"Code": "0047801",
"Name": "Военная подготовка",
"TeacherFull": "Преподаватель УВЦ",
"Teacher": "Преподаватель УВЦ",
"Form": "Очное"
},
"Group": {
"Code": "ПИН-21М",
"Name": "ПИН-21М"
},
"Room": {
"Code": 161,
"Name": "УВЦ2"
}
},
{
"Day": 3,
"DayNumber": 3,
"Time": {
"Time": "7 пара",
"Code": 8,
"TimeFrom": "0001-01-01T20:00:00",
"TimeTo": "0001-01-01T21:30:00"
},
"Class": {
"Code": "0047801",
"Name": "Военная подготовка",
"TeacherFull": "Преподаватель УВЦ",
"Teacher": "Преподаватель УВЦ",
"Form": "Очное"
},
"Group": {
"Code": "ПИН-21М",
"Name": "ПИН-21М"
},
"Room": {
"Code": 161,
"Name": "УВЦ2"
}
},
{
"Day": 4,
"DayNumber": 0,
"Time": {
"Time": "6 пара",
"Code": 7,
"TimeFrom": "0001-01-01T18:20:00",
"TimeTo": "0001-01-01T19:50:00"
},
"Class": {
"Code": "0050755",
"Name": "Проектный менеджмент [Лек]",
"TeacherFull": "Прима Яна Геннадьевна",
"Teacher": "Прима Я.Г.",
"Form": "Очное"
},
"Group": {
"Code": "ПИН-21М",
"Name": "ПИН-21М"
},
"Room": {
"Code": 9,
"Name": "4203 (м)"
}
},
{
"Day": 4,
"DayNumber": 0,
"Time": {
"Time": "7 пара",
"Code": 8,
"TimeFrom": "0001-01-01T20:00:00",
"TimeTo": "0001-01-01T21:30:00"
},
"Class": {
"Code": "0050901",
"Name": "Актуальные вопросы философии техники [Лек]",
"TeacherFull": "Даниелян Наира Владимировна",
"Teacher": "Даниелян Н.В.",
"Form": "Очное"
},
"Group": {
"Code": "ПИН-21М",
"Name": "ПИН-21М"
},
"Room": {
"Code": 7,
"Name": "3104 (м)"
}
},
{
"Day": 4,
"DayNumber": 1,
"Time": {
"Time": "6 пара",
"Code": 7,
"TimeFrom": "0001-01-01T18:20:00",
"TimeTo": "0001-01-01T19:50:00"
},
"Class": {
"Code": "0050755",
"Name": "Проектный менеджмент [Лек]",
"TeacherFull": "Прима Яна Геннадьевна",
"Teacher": "Прима Я.Г.",
"Form": "Очное"
},
"Group": {
"Code": "ПИН-21М",
"Name": "ПИН-21М"
},
"Room": {
"Code": 9,
"Name": "4203 (м)"
}
},
{
"Day": 4,
"DayNumber": 1,
"Time": {
"Time": "7 пара",
"Code": 8,
"TimeFrom": "0001-01-01T20:00:00",
"TimeTo": "0001-01-01T21:30:00"
},
"Class": {
"Code": "0050901",
"Name": "Актуальные вопросы философии техники [Лек]",
"TeacherFull": "Даниелян Наира Владимировна",
"Teacher": "Даниелян Н.В.",
"Form": "Очное"
},
"Group": {
"Code": "ПИН-21М",
"Name": "ПИН-21М"
},
"Room": {
"Code": 7,
"Name": "3104 (м)"
}
},
{
"Day": 4,
"DayNumber": 2,
"Time": {
"Time": "6 пара",
"Code": 7,
"TimeFrom": "0001-01-01T18:20:00",
"TimeTo": "0001-01-01T19:50:00"
},
"Class": {
"Code": "0050755",
"Name": "Проектный менеджмент [Лек]",
"TeacherFull": "Прима Яна Геннадьевна",
"Teacher": "Прима Я.Г.",
"Form": "Очное"
},
"Group": {
"Code": "ПИН-21М",
"Name": "ПИН-21М"
},
"Room": {
"Code": 9,
"Name": "4203 (м)"
}
},
{
"Day": 4,
"DayNumber": 2,
"Time": {
"Time": "7 пара",
"Code": 8,
"TimeFrom": "0001-01-01T20:00:00",
"TimeTo": "0001-01-01T21:30:00"
},
"Class": {
"Code": "0050901",
"Name": "Актуальные вопросы философии техники [Лек]",
"TeacherFull": "Даниелян Наира Владимировна",
"Teacher": "Даниелян Н.В.",
"Form": "Очное"
},
"Group": {
"Code": "ПИН-21М",
"Name": "ПИН-21М"
},
"Room": {
"Code": 7,
"Name": "3104 (м)"
}
},
{
"Day": 4,
"DayNumber": 3,
"Time": {
"Time": "6 пара",
"Code": 7,
"TimeFrom": "0001-01-01T18:20:00",
"TimeTo": "0001-01-01T19:50:00"
},
"Class": {
"Code": "0050755",
"Name": "Проектный менеджмент [Лек]",
"TeacherFull": "Прима Яна Геннадьевна",
"Teacher": "Прима Я.Г.",
"Form": "Очное"
},
"Group": {
"Code": "ПИН-21М",
"Name": "ПИН-21М"
},
"Room": {
"Code": 9,
"Name": "4203 (м)"
}
},
{
"Day": 4,
"DayNumber": 3,
"Time": {
"Time": "7 пара",
"Code": 8,
"TimeFrom": "0001-01-01T20:00:00",
"TimeTo": "0001-01-01T21:30:00"
},
"Class": {
"Code": "0050901",
"Name": "Актуальные вопросы философии техники [Лек]",
"TeacherFull": "Даниелян Наира Владимировна",
"Teacher": "Даниелян Н.В.",
"Form": "Очное"
},
"Group": {
"Code": "ПИН-21М",
"Name": "ПИН-21М"
},
"Room": {
"Code": 7,
"Name": "3104 (м)"
}
},
{
"Day": 5,
"DayNumber": 0,
"Time": {
"Time": "4 пара",
"Code": 5,
"TimeFrom": "0001-01-01T14:30:00",
"TimeTo": "0001-01-01T16:00:00"
},
"Class": {
"Code": "0047801",
"Name": "Военная подготовка",
"TeacherFull": "Преподаватель УВЦ",
"Teacher": "Преподаватель УВЦ",
"Form": "Очное"
},
"Group": {
"Code": "ПИН-21М",
"Name": "ПИН-21М"
},
"Room": {
"Code": 161,
"Name": "УВЦ2"
}
},
{
"Day": 5,
"DayNumber": 0,
"Time": {
"Time": "5 пара",
"Code": 6,
"TimeFrom": "0001-01-01T16:10:00",
"TimeTo": "0001-01-01T17:40:00"
},
"Class": {
"Code": "0047801",
"Name": "Военная подготовка",
"TeacherFull": "Преподаватель УВЦ",
"Teacher": "Преподаватель УВЦ",
"Form": "Очное"
},
"Group": {
"Code": "ПИН-21М",
"Name": "ПИН-21М"
},
"Room": {
"Code": 161,
"Name": "УВЦ2"
}
},
{
"Day": 5,
"DayNumber": 0,
"Time": {
"Time": "2 пара",
"Code": 2,
"TimeFrom": "0001-01-01T10:40:00",
"TimeTo": "0001-01-01T12:10:00"
},
"Class": {
"Code": "0047801",
"Name": "Военная подготовка",
"TeacherFull": "Преподаватель УВЦ",
"Teacher": "Преподаватель УВЦ",
"Form": "Очное"
},
"Group": {
"Code": "ПИН-21М",
"Name": "ПИН-21М"
},
"Room": {
"Code": 161,
"Name": "УВЦ2"
}
},
{
"Day": 5,
"DayNumber": 0,
"Time": {
"Time": "1 пара",
"Code": 1,
"TimeFrom": "0001-01-01T09:00:00",
"TimeTo": "0001-01-01T10:30:00"
},
"Class": {
"Code": "0047801",
"Name": "Военная подготовка",
"TeacherFull": "Преподаватель УВЦ",
"Teacher": "Преподаватель УВЦ",
"Form": "Очное"
},
"Group": {
"Code": "ПИН-21М",
"Name": "ПИН-21М"
},
"Room": {
"Code": 161,
"Name": "УВЦ2"
}
},
{
"Day": 5,
"DayNumber": 0,
"Time": {
"Time": "3 пара ",
"Code": 3,
"TimeFrom": "0001-01-01T12:20:00",
"TimeTo": "0001-01-01T13:50:00"
},
"Class": {
"Code": "0047801",
"Name": "Военная подготовка",
"TeacherFull": "Преподаватель УВЦ",
"Teacher": "Преподаватель УВЦ",
"Form": "Очное"
},
"Group": {
"Code": "ПИН-21М",
"Name": "ПИН-21М"
},
"Room": {
"Code": 161,
"Name": "УВЦ2"
}
},
{
"Day": 5,
"DayNumber": 0,
"Time": {
"Time": "6 пара",
"Code": 7,
"TimeFrom": "0001-01-01T18:20:00",
"TimeTo": "0001-01-01T19:50:00"
},
"Class": {
"Code": "0047801",
"Name": "Военная подготовка",
"TeacherFull": "Преподаватель УВЦ",
"Teacher": "Преподаватель УВЦ",
"Form": "Очное"
},
"Group": {
"Code": "ПИН-21М",
"Name": "ПИН-21М"
},
"Room": {
"Code": 161,
"Name": "УВЦ2"
}
},
{
"Day": 5,
"DayNumber": 0,
"Time": {
"Time": "7 пара",
"Code": 8,
"TimeFrom": "0001-01-01T20:00:00",
"TimeTo": "0001-01-01T21:30:00"
},
"Class": {
"Code": "0047801",
"Name": "Военная подготовка",
"TeacherFull": "Преподаватель УВЦ",
"Teacher": "Преподаватель УВЦ",
"Form": "Очное"
},
"Group": {
"Code": "ПИН-21М",
"Name": "ПИН-21М"
},
"Room": {
"Code": 161,
"Name": "УВЦ2"
}
},
{
"Day": 5,
"DayNumber": 1,
"Time": {
"Time": "6 пара",
"Code": 7,
"TimeFrom": "0001-01-01T18:20:00",
"TimeTo": "0001-01-01T19:50:00"
},
"Class": {
"Code": "0047801",
"Name": "Военная подготовка",
"TeacherFull": "Преподаватель УВЦ",
"Teacher": "Преподаватель УВЦ",
"Form": "Очное"
},
"Group": {
"Code": "ПИН-21М",
"Name": "ПИН-21М"
},
"Room": {
"Code": 161,
"Name": "УВЦ2"
}
},
{
"Day": 5,
"DayNumber": 1,
"Time": {
"Time": "3 пара ",
"Code": 3,
"TimeFrom": "0001-01-01T12:20:00",
"TimeTo": "0001-01-01T13:50:00"
},
"Class": {
"Code": "0047801",
"Name": "Военная подготовка",
"TeacherFull": "Преподаватель УВЦ",
"Teacher": "Преподаватель УВЦ",
"Form": "Очное"
},
"Group": {
"Code": "ПИН-21М",
"Name": "ПИН-21М"
},
"Room": {
"Code": 161,
"Name": "УВЦ2"
}
},
{
"Day": 5,
"DayNumber": 1,
"Time": {
"Time": "7 пара",
"Code": 8,
"TimeFrom": "0001-01-01T20:00:00",
"TimeTo": "0001-01-01T21:30:00"
},
"Class": {
"Code": "0047801",
"Name": "Военная подготовка",
"TeacherFull": "Преподаватель УВЦ",
"Teacher": "Преподаватель УВЦ",
"Form": "Очное"
},
"Group": {
"Code": "ПИН-21М",
"Name": "ПИН-21М"
},
"Room": {
"Code": 161,
"Name": "УВЦ2"
}
},
{
"Day": 5,
"DayNumber": 1,
"Time": {
"Time": "1 пара",
"Code": 1,
"TimeFrom": "0001-01-01T09:00:00",
"TimeTo": "0001-01-01T10:30:00"
},
"Class": {
"Code": "0047801",
"Name": "Военная подготовка",
"TeacherFull": "Преподаватель УВЦ",
"Teacher": "Преподаватель УВЦ",
"Form": "Очное"
},
"Group": {
"Code": "ПИН-21М",
"Name": "ПИН-21М"
},
"Room": {
"Code": 161,
"Name": "УВЦ2"
}
},
{
"Day": 5,
"DayNumber": 1,
"Time": {
"Time": "2 пара",
"Code": 2,
"TimeFrom": "0001-01-01T10:40:00",
"TimeTo": "0001-01-01T12:10:00"
},
"Class": {
"Code": "0047801",
"Name": "Военная подготовка",
"TeacherFull": "Преподаватель УВЦ",
"Teacher": "Преподаватель УВЦ",
"Form": "Очное"
},
"Group": {
"Code": "ПИН-21М",
"Name": "ПИН-21М"
},
"Room": {
"Code": 161,
"Name": "УВЦ2"
}
},
{
"Day": 5,
"DayNumber": 1,
"Time": {
"Time": "5 пара",
"Code": 6,
"TimeFrom": "0001-01-01T16:10:00",
"TimeTo": "0001-01-01T17:40:00"
},
"Class": {
"Code": "0047801",
"Name": "Военная подготовка",
"TeacherFull": "Преподаватель УВЦ",
"Teacher": "Преподаватель УВЦ",
"Form": "Очное"
},
"Group": {
"Code": "ПИН-21М",
"Name": "ПИН-21М"
},
"Room": {
"Code": 161,
"Name": "УВЦ2"
}
},
{
"Day": 5,
"DayNumber": 1,
"Time": {
"Time": "4 пара",
"Code": 5,
"TimeFrom": "0001-01-01T14:30:00",
"TimeTo": "0001-01-01T16:00:00"
},
"Class": {
"Code": "0047801",
"Name": "Военная подготовка",
"TeacherFull": "Преподаватель УВЦ",
"Teacher": "Преподаватель УВЦ",
"Form": "Очное"
},
"Group": {
"Code": "ПИН-21М",
"Name": "ПИН-21М"
},
"Room": {
"Code": 161,
"Name": "УВЦ2"
}
},
{
"Day": 5,
"DayNumber": 2,
"Time": {
"Time": "4 пара",
"Code": 5,
"TimeFrom": "0001-01-01T14:30:00",
"TimeTo": "0001-01-01T16:00:00"
},
"Class": {
"Code": "0047801",
"Name": "Военная подготовка",
"TeacherFull": "Преподаватель УВЦ",
"Teacher": "Преподаватель УВЦ",
"Form": "Очное"
},
"Group": {
"Code": "ПИН-21М",
"Name": "ПИН-21М"
},
"Room": {
"Code": 161,
"Name": "УВЦ2"
}
},
{
"Day": 5,
"DayNumber": 2,
"Time": {
"Time": "5 пара",
"Code": 6,
"TimeFrom": "0001-01-01T16:10:00",
"TimeTo": "0001-01-01T17:40:00"
},
"Class": {
"Code": "0047801",
"Name": "Военная подготовка",
"TeacherFull": "Преподаватель УВЦ",
"Teacher": "Преподаватель УВЦ",
"Form": "Очное"
},
"Group": {
"Code": "ПИН-21М",
"Name": "ПИН-21М"
},
"Room": {
"Code": 161,
"Name": "УВЦ2"
}
},
{
"Day": 5,
"DayNumber": 2,
"Time": {
"Time": "2 пара",
"Code": 2,
"TimeFrom": "0001-01-01T10:40:00",
"TimeTo": "0001-01-01T12:10:00"
},
"Class": {
"Code": "0047801",
"Name": "Военная подготовка",
"TeacherFull": "Преподаватель УВЦ",
"Teacher": "Преподаватель УВЦ",
"Form": "Очное"
},
"Group": {
"Code": "ПИН-21М",
"Name": "ПИН-21М"
},
"Room": {
"Code": 161,
"Name": "УВЦ2"
}
},
{
"Day": 5,
"DayNumber": 2,
"Time": {
"Time": "1 пара",
"Code": 1,
"TimeFrom": "0001-01-01T09:00:00",
"TimeTo": "0001-01-01T10:30:00"
},
"Class": {
"Code": "0047801",
"Name": "Военная подготовка",
"TeacherFull": "Преподаватель УВЦ",
"Teacher": "Преподаватель УВЦ",
"Form": "Очное"
},
"Group": {
"Code": "ПИН-21М",
"Name": "ПИН-21М"
},
"Room": {
"Code": 161,
"Name": "УВЦ2"
}
},
{
"Day": 5,
"DayNumber": 2,
"Time": {
"Time": "7 пара",
"Code": 8,
"TimeFrom": "0001-01-01T20:00:00",
"TimeTo": "0001-01-01T21:30:00"
},
"Class": {
"Code": "0047801",
"Name": "Военная подготовка",
"TeacherFull": "Преподаватель УВЦ",
"Teacher": "Преподаватель УВЦ",
"Form": "Очное"
},
"Group": {
"Code": "ПИН-21М",
"Name": "ПИН-21М"
},
"Room": {
"Code": 161,
"Name": "УВЦ2"
}
},
{
"Day": 5,
"DayNumber": 2,
"Time": {
"Time": "3 пара ",
"Code": 3,
"TimeFrom": "0001-01-01T12:20:00",
"TimeTo": "0001-01-01T13:50:00"
},
"Class": {
"Code": "0047801",
"Name": "Военная подготовка",
"TeacherFull": "Преподаватель УВЦ",
"Teacher": "Преподаватель УВЦ",
"Form": "Очное"
},
"Group": {
"Code": "ПИН-21М",
"Name": "ПИН-21М"
},
"Room": {
"Code": 161,
"Name": "УВЦ2"
}
},
{
"Day": 5,
"DayNumber": 2,
"Time": {
"Time": "6 пара",
"Code": 7,
"TimeFrom": "0001-01-01T18:20:00",
"TimeTo": "0001-01-01T19:50:00"
},
"Class": {
"Code": "0047801",
"Name": "Военная подготовка",
"TeacherFull": "Преподаватель УВЦ",
"Teacher": "Преподаватель УВЦ",
"Form": "Очное"
},
"Group": {
"Code": "ПИН-21М",
"Name": "ПИН-21М"
},
"Room": {
"Code": 161,
"Name": "УВЦ2"
}
},
{
"Day": 5,
"DayNumber": 3,
"Time": {
"Time": "3 пара ",
"Code": 3,
"TimeFrom": "0001-01-01T12:20:00",
"TimeTo": "0001-01-01T13:50:00"
},
"Class": {
"Code": "0047801",
"Name": "Военная подготовка",
"TeacherFull": "Преподаватель УВЦ",
"Teacher": "Преподаватель УВЦ",
"Form": "Очное"
},
"Group": {
"Code": "ПИН-21М",
"Name": "ПИН-21М"
},
"Room": {
"Code": 161,
"Name": "УВЦ2"
}
},
{
"Day": 5,
"DayNumber": 3,
"Time": {
"Time": "6 пара",
"Code": 7,
"TimeFrom": "0001-01-01T18:20:00",
"TimeTo": "0001-01-01T19:50:00"
},
"Class": {
"Code": "0047801",
"Name": "Военная подготовка",
"TeacherFull": "Преподаватель УВЦ",
"Teacher": "Преподаватель УВЦ",
"Form": "Очное"
},
"Group": {
"Code": "ПИН-21М",
"Name": "ПИН-21М"
},
"Room": {
"Code": 161,
"Name": "УВЦ2"
}
},
{
"Day": 5,
"DayNumber": 3,
"Time": {
"Time": "7 пара",
"Code": 8,
"TimeFrom": "0001-01-01T20:00:00",
"TimeTo": "0001-01-01T21:30:00"
},
"Class": {
"Code": "0047801",
"Name": "Военная подготовка",
"TeacherFull": "Преподаватель УВЦ",
"Teacher": "Преподаватель УВЦ",
"Form": "Очное"
},
"Group": {
"Code": "ПИН-21М",
"Name": "ПИН-21М"
},
"Room": {
"Code": 161,
"Name": "УВЦ2"
}
},
{
"Day": 5,
"DayNumber": 3,
"Time": {
"Time": "5 пара",
"Code": 6,
"TimeFrom": "0001-01-01T16:10:00",
"TimeTo": "0001-01-01T17:40:00"
},
"Class": {
"Code": "0047801",
"Name": "Военная подготовка",
"TeacherFull": "Преподаватель УВЦ",
"Teacher": "Преподаватель УВЦ",
"Form": "Очное"
},
"Group": {
"Code": "ПИН-21М",
"Name": "ПИН-21М"
},
"Room": {
"Code": 161,
"Name": "УВЦ2"
}
},
{
"Day": 5,
"DayNumber": 3,
"Time": {
"Time": "1 пара",
"Code": 1,
"TimeFrom": "0001-01-01T09:00:00",
"TimeTo": "0001-01-01T10:30:00"
},
"Class": {
"Code": "0047801",
"Name": "Военная подготовка",
"TeacherFull": "Преподаватель УВЦ",
"Teacher": "Преподаватель УВЦ",
"Form": "Очное"
},
"Group": {
"Code": "ПИН-21М",
"Name": "ПИН-21М"
},
"Room": {
"Code": 161,
"Name": "УВЦ2"
}
},
{
"Day": 5,
"DayNumber": 3,
"Time": {
"Time": "2 пара",
"Code": 2,
"TimeFrom": "0001-01-01T10:40:00",
"TimeTo": "0001-01-01T12:10:00"
},
"Class": {
"Code": "0047801",
"Name": "Военная подготовка",
"TeacherFull": "Преподаватель УВЦ",
"Teacher": "Преподаватель УВЦ",
"Form": "Очное"
},
"Group": {
"Code": "ПИН-21М",
"Name": "ПИН-21М"
},
"Room": {
"Code": 161,
"Name": "УВЦ2"
}
},
{
"Day": 5,
"DayNumber": 3,
"Time": {
"Time": "4 пара",
"Code": 5,
"TimeFrom": "0001-01-01T14:30:00",
"TimeTo": "0001-01-01T16:00:00"
},
"Class": {
"Code": "0047801",
"Name": "Военная подготовка",
"TeacherFull": "Преподаватель УВЦ",
"Teacher": "Преподаватель УВЦ",
"Form": "Очное"
},
"Group": {
"Code": "ПИН-21М",
"Name": "ПИН-21М"
},
"Room": {
"Code": 161,
"Name": "УВЦ2"
}
},
{
"Day": 6,
"DayNumber": 0,
"Time": {
"Time": "2 пара",
"Code": 2,
"TimeFrom": "0001-01-01T10:40:00",
"TimeTo": "0001-01-01T12:10:00"
},
"Class": {
"Code": "0050742",
"Name": "Математическая лингвистика и обработка естественного языка [Лаб]",
"TeacherFull": "Городилов Алексей Владиславович",
"Teacher": "Городилов А.В.",
"Form": "Очное"
},
"Group": {
"Code": "ПИН-21М",
"Name": "ПИН-21М"
},
"Room": {
"Code": 45,
"Name": "3125 к (м)"
}
},
{
"Day": 6,
"DayNumber": 0,
"Time": {
"Time": "1 пара",
"Code": 1,
"TimeFrom": "0001-01-01T09:00:00",
"TimeTo": "0001-01-01T10:30:00"
},
"Class": {
"Code": "0050742",
"Name": "Математическая лингвистика и обработка естественного языка [Лаб]",
"TeacherFull": "Городилов Алексей Владиславович",
"Teacher": "Городилов А.В.",
"Form": "Очное"
},
"Group": {
"Code": "ПИН-21М",
"Name": "ПИН-21М"
},
"Room": {
"Code": 45,
"Name": "3125 к (м)"
}
},
{
"Day": 6,
"DayNumber": 0,
"Time": {
"Time": "5 пара",
"Code": 6,
"TimeFrom": "0001-01-01T16:10:00",
"TimeTo": "0001-01-01T17:40:00"
},
"Class": {
"Code": "0051752",
"Name": "Разработка мобильных приложений [Лек]",
"TeacherFull": "Городилов Алексей Владиславович",
"Teacher": "Городилов А.В.",
"Form": "Очное"
},
"Group": {
"Code": "ПИН-21М",
"Name": "ПИН-21М"
},
"Room": {
"Code": 8,
"Name": "3216 (м)"
}
},
{
"Day": 6,
"DayNumber": 0,
"Time": {
"Time": "3 пара ",
"Code": 3,
"TimeFrom": "0001-01-01T12:20:00",
"TimeTo": "0001-01-01T13:50:00"
},
"Class": {
"Code": "0052493",
"Name": "Проектный менеджмент [Пр]",
"TeacherFull": "Игрунова Оксана Михайловна",
"Teacher": "Игрунова О.М.",
"Form": "Очное"
},
"Group": {
"Code": "ПИН-21М",
"Name": "ПИН-21М"
},
"Room": {
"Code": 52,
"Name": "3240"
}
},
{
"Day": 6,
"DayNumber": 1,
"Time": {
"Time": "6 пара",
"Code": 7,
"TimeFrom": "0001-01-01T18:20:00",
"TimeTo": "0001-01-01T19:50:00"
},
"Class": {
"Code": "0051436",
"Name": "Актуальные вопросы философии техники [Пр]",
"TeacherFull": "Комаров Александр Иванович",
"Teacher": "Комаров А.И.",
"Form": "Очное"
},
"Group": {
"Code": "ПИН-21М",
"Name": "ПИН-21М"
},
"Room": {
"Code": 41,
"Name": "3109 (м)"
}
},
{
"Day": 6,
"DayNumber": 1,
"Time": {
"Time": "2 пара",
"Code": 2,
"TimeFrom": "0001-01-01T10:40:00",
"TimeTo": "0001-01-01T12:10:00"
},
"Class": {
"Code": "0052493",
"Name": "Проектный менеджмент [Пр]",
"TeacherFull": "Игрунова Оксана Михайловна",
"Teacher": "Игрунова О.М.",
"Form": "Очное"
},
"Group": {
"Code": "ПИН-21М",
"Name": "ПИН-21М"
},
"Room": {
"Code": 58,
"Name": "3304"
}
},
{
"Day": 6,
"DayNumber": 2,
"Time": {
"Time": "1 пара",
"Code": 1,
"TimeFrom": "0001-01-01T09:00:00",
"TimeTo": "0001-01-01T10:30:00"
},
"Class": {
"Code": "0050742",
"Name": "Математическая лингвистика и обработка естественного языка [Лаб]",
"TeacherFull": "Городилов Алексей Владиславович",
"Teacher": "Городилов А.В.",
"Form": "Очное"
},
"Group": {
"Code": "ПИН-21М",
"Name": "ПИН-21М"
},
"Room": {
"Code": 45,
"Name": "3125 к (м)"
}
},
{
"Day": 6,
"DayNumber": 2,
"Time": {
"Time": "2 пара",
"Code": 2,
"TimeFrom": "0001-01-01T10:40:00",
"TimeTo": "0001-01-01T12:10:00"
},
"Class": {
"Code": "0050742",
"Name": "Математическая лингвистика и обработка естественного языка [Лаб]",
"TeacherFull": "Городилов Алексей Владиславович",
"Teacher": "Городилов А.В.",
"Form": "Очное"
},
"Group": {
"Code": "ПИН-21М",
"Name": "ПИН-21М"
},
"Room": {
"Code": 45,
"Name": "3125 к (м)"
}
},
{
"Day": 6,
"DayNumber": 2,
"Time": {
"Time": "5 пара",
"Code": 6,
"TimeFrom": "0001-01-01T16:10:00",
"TimeTo": "0001-01-01T17:40:00"
},
"Class": {
"Code": "0051752",
"Name": "Разработка мобильных приложений [Лек]",
"TeacherFull": "Городилов Алексей Владиславович",
"Teacher": "Городилов А.В.",
"Form": "Очное"
},
"Group": {
"Code": "ПИН-21М",
"Name": "ПИН-21М"
},
"Room": {
"Code": 8,
"Name": "3216 (м)"
}
},
{
"Day": 6,
"DayNumber": 2,
"Time": {
"Time": "3 пара ",
"Code": 3,
"TimeFrom": "0001-01-01T12:20:00",
"TimeTo": "0001-01-01T13:50:00"
},
"Class": {
"Code": "0052493",
"Name": "Проектный менеджмент [Пр]",
"TeacherFull": "Игрунова Оксана Михайловна",
"Teacher": "Игрунова О.М.",
"Form": "Очное"
},
"Group": {
"Code": "ПИН-21М",
"Name": "ПИН-21М"
},
"Room": {
"Code": 52,
"Name": "3240"
}
},
{
"Day": 6,
"DayNumber": 3,
"Time": {
"Time": "6 пара",
"Code": 7,
"TimeFrom": "0001-01-01T18:20:00",
"TimeTo": "0001-01-01T19:50:00"
},
"Class": {
"Code": "0051436",
"Name": "Актуальные вопросы философии техники [Пр]",
"TeacherFull": "Комаров Александр Иванович",
"Teacher": "Комаров А.И.",
"Form": "Очное"
},
"Group": {
"Code": "ПИН-21М",
"Name": "ПИН-21М"
},
"Room": {
"Code": 47,
"Name": "3207 (м)"
}
},
{
"Day": 6,
"DayNumber": 3,
"Time": {
"Time": "2 пара",
"Code": 2,
"TimeFrom": "0001-01-01T10:40:00",
"TimeTo": "0001-01-01T12:10:00"
},
"Class": {
"Code": "0052493",
"Name": "Проектный менеджмент [Пр]",
"TeacherFull": "Игрунова Оксана Михайловна",
"Teacher": "Игрунова О.М.",
"Form": "Очное"
},
"Group": {
"Code": "ПИН-21М",
"Name": "ПИН-21М"
},
"Room": {
"Code": 58,
"Name": "3304"
}
}
],
"Semestr": "Весенний семестр 2021-2022 г."
}